ogc/na/__init__.py
ogc/na/_version.py
ogc/na/annotate_schema.py
ogc/na/domain_config.py
ogc/na/download.py
ogc/na/exceptions.py
ogc/na/gsp.py
ogc/na/ingest_json.py
ogc/na/models.py
ogc/na/profile.py
ogc/na/provenance.py
ogc/na/update_vocabs.py
ogc/na/util.py
ogc/na/validation.py
ogc/na/input_filters/__init__.py
ogc/na/input_filters/csv.py
ogc/na/input_filters/xlsx.py
ogc/na/input_filters/xml.py
ogc_na-0.5.16.dist-info/licenses/LICENSE
ogc_na-0.5.16.dist-info/METADATA
ogc_na-0.5.16.dist-info/WHEEL
ogc_na-0.5.16.dist-info/top_level.txt
ogc_na-0.5.16.dist-info/RECORD
