Metadata-Version: 2.4
Name: ogc_na
Version: 0.5.16
Summary: OGC Naming Authority tools
Author-email: Rob Atkinson <ratkinson@ogc.org>, Piotr Zaborowski <pzaborowski@ogc.org>, Alejandro Villar <avillar@ogc.org>
License-Expression: Apache-2.0
Project-URL: Homepage, https://github.com/opengeospatial/ogc-na-tools/
Project-URL: Documentation, https://opengeospatial.github.io/ogc-na-tools/
Project-URL: Repository, https://github.com/opengeospatial/ogc-na-tools.git
Keywords: ogc,ogc-na,naming authority,ogc rainbow,definitions server
Classifier: Development Status :: 4 - Beta
Classifier: Topic :: Scientific/Engineering
Classifier: Topic :: Utilities
Classifier: Topic :: Software Development :: Libraries
Requires-Python: >=3.7
License-File: LICENSE
Requires-Dist: pyshacl>=0.19
Requires-Dist: rdflib>=6.3.0
Requires-Dist: html5lib
Requires-Dist: jq
Requires-Dist: jsonpath-ng
Requires-Dist: PyYAML
Requires-Dist: wcmatch
Requires-Dist: requests>=2.30
Requires-Dist: jsonschema
Requires-Dist: GitPython>=3.1.32
Requires-Dist: rfc3987
Requires-Dist: requests-cache
Requires-Dist: xmltodict
Requires-Dist: jsonpointer~=2.4
Requires-Dist: openpyxl~=3.1.5
Requires-Dist: setuptools
Provides-Extra: dev
Requires-Dist: mkdocs>=1.4.2; extra == "dev"
Requires-Dist: mkdocs-autorefs; extra == "dev"
Requires-Dist: mkdocs-gen-files; extra == "dev"
Requires-Dist: mkdocs-literate-nav; extra == "dev"
Requires-Dist: mkdocs-material; extra == "dev"
Requires-Dist: mkdocs-material-extensions; extra == "dev"
Requires-Dist: mkdocs-pymdownx-material-extras; extra == "dev"
Requires-Dist: mkdocs-section-index; extra == "dev"
Requires-Dist: mkdocstrings; extra == "dev"
Requires-Dist: mkdocstrings-python; extra == "dev"
Requires-Dist: mkdocs-markdownextradata-plugin; extra == "dev"
Dynamic: license-file
